langchain_weaviate/__init__.py
langchain_weaviate/_math.py
langchain_weaviate/py.typed
langchain_weaviate/utils.py
langchain_weaviate/vectorstores.py
langchain_weaviate-0.0.6.dist-info/LICENSE
langchain_weaviate-0.0.6.dist-info/METADATA
langchain_weaviate-0.0.6.dist-info/WHEEL
langchain_weaviate-0.0.6.dist-info/RECORD
